malpy/__init__.py
malpy/__main__.py
malpy/actionrunner.py
malpy/cycleanalyzer.py
malpy/parser.py
malpy/runner.py
malpy-1.1.0.dist-info/DESCRIPTION.rst
malpy-1.1.0.dist-info/METADATA
malpy-1.1.0.dist-info/RECORD
malpy-1.1.0.dist-info/WHEEL
malpy-1.1.0.dist-info/entry_points.txt
malpy-1.1.0.dist-info/metadata.json
malpy-1.1.0.dist-info/top_level.txt
