Metadata-Version: 2.0
Name: malpy
Version: 1.1.0
Summary: Minimal Assembly Language Virtual Machine
Home-page: https://github.com/LSmit202/Mal-Py
Author: Luke Smith
Author-email: lsmit202@musdenver.edu
License: BSD
Platform: UNKNOWN
Provides-Extra: docstest
Requires-Dist: doc8; extra == 'docstest'
Requires-Dist: pyenchant; extra == 'docstest'
Requires-Dist: readme-renderer (>=16.0); extra == 'docstest'
Requires-Dist: sphinx; extra == 'docstest'
Requires-Dist: sphinx-rtd-theme; extra == 'docstest'
Requires-Dist: sphinxcontrib-spelling; extra == 'docstest'
Provides-Extra: pep8test
Requires-Dist: flake8; extra == 'pep8test'
Requires-Dist: flake8-import-order; extra == 'pep8test'
Requires-Dist: pep8-naming; extra == 'pep8test'
Provides-Extra: test
Requires-Dist: pytest; extra == 'test'
